odoo9_addon_sale_start_end_dates-9.0.1.0.0-py2.7-nspkg.pth
odoo_addons/sale_start_end_dates/__openerp__.py
odoo_addons/sale_start_end_dates/__init__.py
odoo_addons/sale_start_end_dates/README.rst
odoo_addons/sale_start_end_dates/models/sale.py
odoo_addons/sale_start_end_dates/models/__init__.py
odoo_addons/sale_start_end_dates/i18n/zh_CN.po
odoo_addons/sale_start_end_dates/i18n/it.po
odoo_addons/sale_start_end_dates/i18n/es.po
odoo_addons/sale_start_end_dates/i18n/sl.po
odoo_addons/sale_start_end_dates/i18n/sale_start_end_dates.pot
odoo_addons/sale_start_end_dates/i18n/de.po
odoo_addons/sale_start_end_dates/i18n/fr.po
odoo_addons/sale_start_end_dates/i18n/fi.po
odoo_addons/sale_start_end_dates/views/sale_order.xml
odoo_addons/sale_start_end_dates/demo/sale_demo.xml
odoo_addons/sale_start_end_dates/static/description/icon.png
odoo9_addon_sale_start_end_dates-9.0.1.0.0.dist-info/top_level.txt
odoo9_addon_sale_start_end_dates-9.0.1.0.0.dist-info/WHEEL
odoo9_addon_sale_start_end_dates-9.0.1.0.0.dist-info/RECORD
odoo9_addon_sale_start_end_dates-9.0.1.0.0.dist-info/metadata.json
odoo9_addon_sale_start_end_dates-9.0.1.0.0.dist-info/DESCRIPTION.rst
odoo9_addon_sale_start_end_dates-9.0.1.0.0.dist-info/METADATA
odoo9_addon_sale_start_end_dates-9.0.1.0.0.dist-info/namespace_packages.txt
