Metadata-Version: 2.0
Name: odoo9-addon-sale-start-end-dates
Version: 9.0.1.0.0
Summary: Adds start date and end date on sale order lines
Home-page: http://www.akretion.com
Author: UNKNOWN
Author-email: UNKNOWN
License: AGPL-3
Platform: UNKNOWN
Requires-Dist: odoo (<9.1a,>=9.0a)
Requires-Dist: odoo9-addon-account-invoice-start-end-dates
Classifier: Programming Language :: Python :: 2.7
Classifier: Framework :: Odoo
Classifier: License :: OSI Approved :: GNU Affero General Public License v3
